netclop/__init__.py
netclop/centrality/__init__.py
netclop/centrality/centrality.py
netclop/centrality/centrality_compute.py
netclop/cli/__init__.py
netclop/cli/__main__.py
netclop/cli/commands.py
netclop/cli/files.py
netclop/constants.py
netclop/ensemble/__init__.py
netclop/ensemble/ensemble.py
netclop/ensemble/netutils.py
netclop/ensemble/sigclu.py
netclop/ensemble/upsetplot.py
netclop/exceptions.py
netclop/geo/__init__.py
netclop/geo/net.py
netclop/geo/plot.py
netclop/log.py
netclop/typing.py
netclop-2.2.1.dist-info/LICENSE
netclop-2.2.1.dist-info/METADATA
netclop-2.2.1.dist-info/WHEEL
netclop-2.2.1.dist-info/entry_points.txt
netclop-2.2.1.dist-info/RECORD
