Metadata-Version: 2.1
Name: netclop
Version: 2.2.1
Summary: Network clustering operations (for geophysical fluid transport)
Author: KarstenEconomou
Author-email: KarstenEconomou@dal.ca
Requires-Python: >=3.12,<4.0
Classifier: Programming Language :: Python :: 3
Classifier: Programming Language :: Python :: 3.12
Classifier: Programming Language :: Python :: 3.13
Requires-Dist: click (>=8.1.7,<9.0.0)
Requires-Dist: geopandas (>=0.14.2,<0.15.0)
Requires-Dist: h3 (==4.0.0b2)
Requires-Dist: infomap (>=2.7.1,<3.0.0)
Requires-Dist: kaleido (==0.2.1)
Requires-Dist: loguru (>=0.7.2,<0.8.0)
Requires-Dist: networkx (>=3.2.1,<4.0.0)
Requires-Dist: numpy (>=1.26.3,<2.0.0)
Requires-Dist: pandas (>=2.1.4,<3.0.0)
Requires-Dist: plotly (>=5.18.0,<6.0.0)
Requires-Dist: pyyaml (>=6.0.1,<7.0.0)
Requires-Dist: seaborn (>=0.13.2,<0.14.0)
Requires-Dist: tqdm (>=4.67.0,<5.0.0)
Requires-Dist: upsetplot (>=0.9.0,<0.10.0)
